README.md
setup.py
PyTsetlinMachineCUDA/__init__.py
PyTsetlinMachineCUDA/kernels.py
PyTsetlinMachineCUDA/tm.py
PyTsetlinMachineCUDA/tools.py
PyTsetlinMachineCUDA.egg-info/PKG-INFO
PyTsetlinMachineCUDA.egg-info/SOURCES.txt
PyTsetlinMachineCUDA.egg-info/dependency_links.txt
PyTsetlinMachineCUDA.egg-info/top_level.txt