Metadata-Version: 1.0
Name: PyTsetlinMachineCUDA
Version: 0.1.1
Summary: A Massively Parallel and Asynchronous Architecture for Logic-based AI.
Home-page: https://github.com/cair/pyTsetlinMachineCUDA/
Author: Ole-Christoffer Granmo
Author-email: ole.granmo@uia.no
License: MIT
Keywords: pattern-recognition cuda machine-learning interpretable-machine-learning rule-based-machine-learning propositional-logic tsetlin-machine regression convolution
Platform: UNKNOWN
